<?xml version="1.0" encoding="UTF-8"?>
<!DOCTYPE plist PUBLIC "-//Apple//DTD PLIST 1.0//EN" "http://www.apple.com/DTDs/PropertyList-1.0.dtd">
<plist version="1.0">
<dict>
	<key>WFWorkflowActions</key>
	<array>
		<dict>
			<key>WFWorkflowActionIdentifier</key>
			<string>is.workflow.actions.comment</string>
			<key>WFWorkflowActionParameters</key>
			<dict>
				<key>WFCommentActionText</key>
				<string>Bustl. Updater

Auto-Updater for Bustl. sponsored Integrity Framwork tools.
———
{"name":"Bustl. Updater","auuid":"748AD281-D6A6-43F3-A1E6-E2DABDB2CEA2","version":"10.3.1"}</string>
			</dict>
		</dict>
		<dict>
			<key>WFWorkflowActionIdentifier</key>
			<string>is.workflow.actions.dictionary</string>
			<key>WFWorkflowActionParameters</key>
			<dict>
				<key>UUID</key>
				<string>189935CB-6A0B-41B7-9E24-5CC90C717D96</string>
				<key>WFItems</key>
				<dict>
					<key>Value</key>
					<dict>
						<key>WFDictionaryFieldValueItems</key>
						<array>
							<dict>
								<key>WFItemType</key>
								<integer>0</integer>
								<key>WFKey</key>
								<dict>
									<key>Value</key>
									<dict>
										<key>string</key>
										<string>name</string>
									</dict>
									<key>WFSerializationType</key>
									<string>WFTextTokenString</string>
								</dict>
								<key>WFValue</key>
								<dict>
									<key>Value</key>
									<dict>
										<key>string</key>
										<string>Bustl. Updater</string>
									</dict>
									<key>WFSerializationType</key>
									<string>WFTextTokenString</string>
								</dict>
							</dict>
							<dict>
								<key>WFItemType</key>
								<integer>0</integer>
								<key>WFKey</key>
								<dict>
									<key>Value</key>
									<dict>
										<key>string</key>
										<string>auuid</string>
									</dict>
									<key>WFSerializationType</key>
									<string>WFTextTokenString</string>
								</dict>
								<key>WFValue</key>
								<dict>
									<key>Value</key>
									<dict>
										<key>string</key>
										<string>748AD281-D6A6-43F3-A1E6-E2DABDB2CEA2</string>
									</dict>
									<key>WFSerializationType</key>
									<string>WFTextTokenString</string>
								</dict>
							</dict>
							<dict>
								<key>WFItemType</key>
								<integer>0</integer>
								<key>WFKey</key>
								<dict>
									<key>Value</key>
									<dict>
										<key>string</key>
										<string>version</string>
									</dict>
									<key>WFSerializationType</key>
									<string>WFTextTokenString</string>
								</dict>
								<key>WFValue</key>
								<dict>
									<key>Value</key>
									<dict>
										<key>string</key>
										<string>3.14</string>
									</dict>
									<key>WFSerializationType</key>
									<string>WFTextTokenString</string>
								</dict>
							</dict>
							<dict>
								<key>WFItemType</key>
								<integer>4</integer>
								<key>WFKey</key>
								<dict>
									<key>Value</key>
									<dict>
										<key>string</key>
										<string>quiet</string>
									</dict>
									<key>WFSerializationType</key>
									<string>WFTextTokenString</string>
								</dict>
								<key>WFValue</key>
								<dict>
									<key>Value</key>
									<false/>
									<key>WFSerializationType</key>
									<string>WFNumberSubstitutableState</string>
								</dict>
							</dict>
							<dict>
								<key>WFItemType</key>
								<integer>0</integer>
								<key>WFKey</key>
								<dict>
									<key>Value</key>
									<dict>
										<key>string</key>
										<string>description</string>
									</dict>
									<key>WFSerializationType</key>
									<string>WFTextTokenString</string>
								</dict>
								<key>WFValue</key>
								<dict>
									<key>Value</key>
									<dict>
										<key>string</key>
										<string>Auto-Updater for Bustl. sponsored Integrity Framwork tools.</string>
									</dict>
									<key>WFSerializationType</key>
									<string>WFTextTokenString</string>
								</dict>
							</dict>
							<dict>
								<key>WFItemType</key>
								<integer>4</integer>
								<key>WFKey</key>
								<dict>
									<key>Value</key>
									<dict>
										<key>string</key>
										<string>true</string>
									</dict>
									<key>WFSerializationType</key>
									<string>WFTextTokenString</string>
								</dict>
								<key>WFValue</key>
								<dict>
									<key>Value</key>
									<true/>
									<key>WFSerializationType</key>
									<string>WFNumberSubstitutableState</string>
								</dict>
							</dict>
							<dict>
								<key>WFItemType</key>
								<integer>0</integer>
								<key>WFKey</key>
								<dict>
									<key>Value</key>
									<dict>
										<key>string</key>
										<string>id</string>
									</dict>
									<key>WFSerializationType</key>
									<string>WFTextTokenString</string>
								</dict>
								<key>WFValue</key>
								<dict>
									<key>Value</key>
									<dict>
										<key>string</key>
										<string>com.shortcutspro.updater</string>
									</dict>
									<key>WFSerializationType</key>
									<string>WFTextTokenString</string>
								</dict>
							</dict>
							<dict>
								<key>WFItemType</key>
								<integer>1</integer>
								<key>WFKey</key>
								<dict>
									<key>Value</key>
									<dict>
										<key>string</key>
										<string>author</string>
									</dict>
									<key>WFSerializationType</key>
									<string>WFTextTokenString</string>
								</dict>
								<key>WFValue</key>
								<dict>
									<key>Value</key>
									<dict>
										<key>Value</key>
										<dict>
											<key>WFDictionaryFieldValueItems</key>
											<array>
												<dict>
													<key>WFItemType</key>
													<integer>0</integer>
													<key>WFKey</key>
													<dict>
														<key>Value</key>
														<dict>
															<key>string</key>
															<string>name</string>
														</dict>
														<key>WFSerializationType</key>
														<string>WFTextTokenString</string>
													</dict>
													<key>WFValue</key>
													<dict>
														<key>Value</key>
														<dict>
															<key>string</key>
															<string>scottdwr</string>
														</dict>
														<key>WFSerializationType</key>
														<string>WFTextTokenString</string>
													</dict>
												</dict>
												<dict>
													<key>WFItemType</key>
													<integer>0</integer>
													<key>WFKey</key>
													<dict>
														<key>Value</key>
														<dict>
															<key>string</key>
															<string>link</string>
														</dict>
														<key>WFSerializationType</key>
														<string>WFTextTokenString</string>
													</dict>
													<key>WFValue</key>
													<dict>
														<key>Value</key>
														<dict>
															<key>string</key>
															<string>https://routinehub.co/user/scottdwr/</string>
														</dict>
														<key>WFSerializationType</key>
														<string>WFTextTokenString</string>
													</dict>
												</dict>
											</array>
										</dict>
										<key>WFSerializationType</key>
										<string>WFDictionaryFieldValue</string>
									</dict>
									<key>WFSerializationType</key>
									<string>WFDictionaryFieldValue</string>
								</dict>
							</dict>
							<dict>
								<key>WFItemType</key>
								<integer>4</integer>
								<key>WFKey</key>
								<dict>
									<key>Value</key>
									<dict>
										<key>string</key>
										<string>false</string>
									</dict>
									<key>WFSerializationType</key>
									<string>WFTextTokenString</string>
								</dict>
								<key>WFValue</key>
								<dict>
									<key>Value</key>
									<false/>
									<key>WFSerializationType</key>
									<string>WFNumberSubstitutableState</string>
								</dict>
							</dict>
							<dict>
								<key>WFItemType</key>
								<integer>2</integer>
								<key>WFKey</key>
								<dict>
									<key>Value</key>
									<dict>
										<key>string</key>
										<string>category</string>
									</dict>
									<key>WFSerializationType</key>
									<string>WFTextTokenString</string>
								</dict>
								<key>WFValue</key>
								<dict>
									<key>Value</key>
									<array>
										<string>utilities</string>
									</array>
									<key>WFSerializationType</key>
									<string>WFArrayParameterState</string>
								</dict>
							</dict>
							<dict>
								<key>WFItemType</key>
								<integer>4</integer>
								<key>WFKey</key>
								<dict>
									<key>Value</key>
									<dict>
										<key>string</key>
										<string>integrity</string>
									</dict>
									<key>WFSerializationType</key>
									<string>WFTextTokenString</string>
								</dict>
								<key>WFValue</key>
								<dict>
									<key>Value</key>
									<true/>
									<key>WFSerializationType</key>
									<string>WFNumberSubstitutableState</string>
								</dict>
							</dict>
						</array>
					</dict>
					<key>WFSerializationType</key>
					<string>WFDictionaryFieldValue</string>
				</dict>
			</dict>
		</dict>
		<dict>
			<key>WFWorkflowActionIdentifier</key>
			<string>is.workflow.actions.comment</string>
			<key>WFWorkflowActionParameters</key>
			<dict>
				<key>WFCommentActionText</key>
				<string>io.bustl.cutz.bustl-updater
</string>
			</dict>
		</dict>
		<dict>
			<key>WFWorkflowActionIdentifier</key>
			<string>is.workflow.actions.gettext</string>
			<key>WFWorkflowActionParameters</key>
			<dict>
				<key>CustomOutputName</key>
				<string>Shortcut Input</string>
				<key>UUID</key>
				<string>D7F8053D-5EF0-423F-9398-0AF5A67B62DC</string>
				<key>WFTextActionText</key>
				<dict>
					<key>Value</key>
					<dict>
						<key>attachmentsByRange</key>
						<dict>
							<key>{0, 1}</key>
							<dict>
								<key>Type</key>
								<string>ExtensionInput</string>
							</dict>
						</dict>
						<key>string</key>
						<string>￼</string>
					</dict>
					<key>WFSerializationType</key>
					<string>WFTextTokenString</string>
				</dict>
			</dict>
		</dict>
		<dict>
			<key>WFWorkflowActionIdentifier</key>
			<string>is.workflow.actions.conditional</string>
			<key>WFWorkflowActionParameters</key>
			<dict>
				<key>GroupingIdentifier</key>
				<string>179E0CB2-810D-4A5F-A86C-666541D87E98</string>
				<key>WFCondition</key>
				<integer>4</integer>
				<key>WFConditionalActionString</key>
				<string>identify</string>
				<key>WFControlFlowMode</key>
				<integer>0</integer>
				<key>WFInput</key>
				<dict>
					<key>Type</key>
					<string>Variable</string>
					<key>Variable</key>
					<dict>
						<key>Value</key>
						<dict>
							<key>OutputName</key>
							<string>Shortcut Input</string>
							<key>OutputUUID</key>
							<string>D7F8053D-5EF0-423F-9398-0AF5A67B62DC</string>
							<key>Type</key>
							<string>ActionOutput</string>
						</dict>
						<key>WFSerializationType</key>
						<string>WFTextTokenAttachment</string>
					</dict>
				</dict>
			</dict>
		</dict>
		<dict>
			<key>WFWorkflowActionIdentifier</key>
			<string>is.workflow.actions.output</string>
			<key>WFWorkflowActionParameters</key>
			<dict>
				<key>UUID</key>
				<string>A4D10AB6-A5FF-4C79-A00E-3F39C3BB2AC8</string>
				<key>WFOutput</key>
				<dict>
					<key>Value</key>
					<dict>
						<key>attachmentsByRange</key>
						<dict>
							<key>{0, 1}</key>
							<dict>
								<key>OutputName</key>
								<string>Dictionary</string>
								<key>OutputUUID</key>
								<string>189935CB-6A0B-41B7-9E24-5CC90C717D96</string>
								<key>Type</key>
								<string>ActionOutput</string>
							</dict>
						</dict>
						<key>string</key>
						<string>￼</string>
					</dict>
					<key>WFSerializationType</key>
					<string>WFTextTokenString</string>
				</dict>
			</dict>
		</dict>
		<dict>
			<key>WFWorkflowActionIdentifier</key>
			<string>is.workflow.actions.conditional</string>
			<key>WFWorkflowActionParameters</key>
			<dict>
				<key>GroupingIdentifier</key>
				<string>179E0CB2-810D-4A5F-A86C-666541D87E98</string>
				<key>WFControlFlowMode</key>
				<integer>1</integer>
			</dict>
		</dict>
		<dict>
			<key>WFWorkflowActionIdentifier</key>
			<string>is.workflow.actions.conditional</string>
			<key>WFWorkflowActionParameters</key>
			<dict>
				<key>GroupingIdentifier</key>
				<string>F54ED468-8DAA-4B2B-AAA2-481CC610297F</string>
				<key>WFCondition</key>
				<integer>100</integer>
				<key>WFControlFlowMode</key>
				<integer>0</integer>
				<key>WFInput</key>
				<dict>
					<key>Type</key>
					<string>Variable</string>
					<key>Variable</key>
					<dict>
						<key>Value</key>
						<dict>
							<key>OutputName</key>
							<string>Shortcut Input</string>
							<key>OutputUUID</key>
							<string>D7F8053D-5EF0-423F-9398-0AF5A67B62DC</string>
							<key>Type</key>
							<string>ActionOutput</string>
						</dict>
						<key>WFSerializationType</key>
						<string>WFTextTokenAttachment</string>
					</dict>
				</dict>
			</dict>
		</dict>
		<dict>
			<key>WFWorkflowActionIdentifier</key>
			<string>is.workflow.actions.comment</string>
			<key>WFWorkflowActionParameters</key>
			<dict>
				<key>WFCommentActionText</key>
				<string>Required	          Optional
—————————————-
   name	              quiet
   auuid	
   version	</string>
			</dict>
		</dict>
		<dict>
			<key>WFWorkflowActionIdentifier</key>
			<string>is.workflow.actions.detect.dictionary</string>
			<key>WFWorkflowActionParameters</key>
			<dict>
				<key>UUID</key>
				<string>700D2E2F-D6FD-458D-ABF5-58C9D5A887EE</string>
				<key>WFInput</key>
				<dict>
					<key>Value</key>
					<dict>
						<key>OutputName</key>
						<string>Shortcut Input</string>
						<key>OutputUUID</key>
						<string>D7F8053D-5EF0-423F-9398-0AF5A67B62DC</string>
						<key>Type</key>
						<string>ActionOutput</string>
					</dict>
					<key>WFSerializationType</key>
					<string>WFTextTokenAttachment</string>
				</dict>
			</dict>
		</dict>
		<dict>
			<key>WFWorkflowActionIdentifier</key>
			<string>is.workflow.actions.conditional</string>
			<key>WFWorkflowActionParameters</key>
			<dict>
				<key>GroupingIdentifier</key>
				<string>F54ED468-8DAA-4B2B-AAA2-481CC610297F</string>
				<key>WFControlFlowMode</key>
				<integer>1</integer>
			</dict>
		</dict>
		<dict>
			<key>WFWorkflowActionIdentifier</key>
			<string>is.workflow.actions.getvariable</string>
			<key>WFWorkflowActionParameters</key>
			<dict>
				<key>WFVariable</key>
				<dict>
					<key>Value</key>
					<dict>
						<key>OutputName</key>
						<string>Dictionary</string>
						<key>OutputUUID</key>
						<string>189935CB-6A0B-41B7-9E24-5CC90C717D96</string>
						<key>Type</key>
						<string>ActionOutput</string>
					</dict>
					<key>WFSerializationType</key>
					<string>WFTextTokenAttachment</string>
				</dict>
			</dict>
		</dict>
		<dict>
			<key>WFWorkflowActionIdentifier</key>
			<string>is.workflow.actions.conditional</string>
			<key>WFWorkflowActionParameters</key>
			<dict>
				<key>GroupingIdentifier</key>
				<string>F54ED468-8DAA-4B2B-AAA2-481CC610297F</string>
				<key>UUID</key>
				<string>22667D5D-6769-4162-8C10-63CA8F306E93</string>
				<key>WFControlFlowMode</key>
				<integer>2</integer>
			</dict>
		</dict>
		<dict>
			<key>WFWorkflowActionIdentifier</key>
			<string>is.workflow.actions.conditional</string>
			<key>WFWorkflowActionParameters</key>
			<dict>
				<key>GroupingIdentifier</key>
				<string>179E0CB2-810D-4A5F-A86C-666541D87E98</string>
				<key>UUID</key>
				<string>2E4AFAF0-89B2-4A3A-B901-3C410AEF3592</string>
				<key>WFControlFlowMode</key>
				<integer>2</integer>
			</dict>
		</dict>
		<dict>
			<key>WFWorkflowActionIdentifier</key>
			<string>is.workflow.actions.setvariable</string>
			<key>WFWorkflowActionParameters</key>
			<dict>
				<key>WFInput</key>
				<dict>
					<key>Value</key>
					<dict>
						<key>OutputName</key>
						<string>If Result</string>
						<key>OutputUUID</key>
						<string>2E4AFAF0-89B2-4A3A-B901-3C410AEF3592</string>
						<key>Type</key>
						<string>ActionOutput</string>
					</dict>
					<key>WFSerializationType</key>
					<string>WFTextTokenAttachment</string>
				</dict>
				<key>WFVariableName</key>
				<string>Input</string>
			</dict>
		</dict>
		<dict>
			<key>WFWorkflowActionIdentifier</key>
			<string>is.workflow.actions.comment</string>
			<key>WFWorkflowActionParameters</key>
			<dict>
				<key>WFCommentActionText</key>
				<string>
</string>
			</dict>
		</dict>
		<dict>
			<key>WFWorkflowActionIdentifier</key>
			<string>is.workflow.actions.getvalueforkey</string>
			<key>WFWorkflowActionParameters</key>
			<dict>
				<key>CustomOutputName</key>
				<string>Name</string>
				<key>UUID</key>
				<string>AD02644F-B0C7-4059-B2B4-EB950B8B834E</string>
				<key>WFDictionaryKey</key>
				<string>name</string>
				<key>WFInput</key>
				<dict>
					<key>Value</key>
					<dict>
						<key>Type</key>
						<string>Variable</string>
						<key>VariableName</key>
						<string>Input</string>
					</dict>
					<key>WFSerializationType</key>
					<string>WFTextTokenAttachment</string>
				</dict>
			</dict>
		</dict>
		<dict>
			<key>WFWorkflowActionIdentifier</key>
			<string>is.workflow.actions.detect.text</string>
			<key>WFWorkflowActionParameters</key>
			<dict>
				<key>CustomOutputName</key>
				<string>Current</string>
				<key>UUID</key>
				<string>6A5E87DE-BA3F-4D24-B3CB-54D0B28C0AD9</string>
				<key>WFInput</key>
				<dict>
					<key>Value</key>
					<dict>
						<key>Aggrandizements</key>
						<array>
							<dict>
								<key>DictionaryKey</key>
								<string>version</string>
								<key>Type</key>
								<string>WFDictionaryValueVariableAggrandizement</string>
							</dict>
						</array>
						<key>Type</key>
						<string>Variable</string>
						<key>VariableName</key>
						<string>Input</string>
					</dict>
					<key>WFSerializationType</key>
					<string>WFTextTokenAttachment</string>
				</dict>
			</dict>
		</dict>
		<dict>
			<key>WFWorkflowActionIdentifier</key>
			<string>is.workflow.actions.setvariable</string>
			<key>WFWorkflowActionParameters</key>
			<dict>
				<key>WFInput</key>
				<dict>
					<key>Value</key>
					<dict>
						<key>OutputName</key>
						<string>Current</string>
						<key>OutputUUID</key>
						<string>6A5E87DE-BA3F-4D24-B3CB-54D0B28C0AD9</string>
						<key>Type</key>
						<string>ActionOutput</string>
					</dict>
					<key>WFSerializationType</key>
					<string>WFTextTokenAttachment</string>
				</dict>
				<key>WFVariableName</key>
				<string>Current</string>
			</dict>
		</dict>
		<dict>
			<key>WFWorkflowActionIdentifier</key>
			<string>is.workflow.actions.detect.text</string>
			<key>WFWorkflowActionParameters</key>
			<dict>
				<key>CustomOutputName</key>
				<string>AUUID</string>
				<key>UUID</key>
				<string>0BE0E935-AD3C-405F-86DA-841E8601E544</string>
				<key>WFInput</key>
				<dict>
					<key>Value</key>
					<dict>
						<key>Aggrandizements</key>
						<array>
							<dict>
								<key>DictionaryKey</key>
								<string>auuid</string>
								<key>Type</key>
								<string>WFDictionaryValueVariableAggrandizement</string>
							</dict>
						</array>
						<key>Type</key>
						<string>Variable</string>
						<key>VariableName</key>
						<string>Input</string>
					</dict>
					<key>WFSerializationType</key>
					<string>WFTextTokenAttachment</string>
				</dict>
			</dict>
		</dict>
		<dict>
			<key>WFWorkflowActionIdentifier</key>
			<string>is.workflow.actions.getvalueforkey</string>
			<key>WFWorkflowActionParameters</key>
			<dict>
				<key>CustomOutputName</key>
				<string>Quiet</string>
				<key>UUID</key>
				<string>6EAA2F70-92AA-4146-80DA-E70C4FB84500</string>
				<key>WFDictionaryKey</key>
				<string>quiet</string>
				<key>WFInput</key>
				<dict>
					<key>Value</key>
					<dict>
						<key>Type</key>
						<string>Variable</string>
						<key>VariableName</key>
						<string>Input</string>
					</dict>
					<key>WFSerializationType</key>
					<string>WFTextTokenAttachment</string>
				</dict>
			</dict>
		</dict>
		<dict>
			<key>WFWorkflowActionIdentifier</key>
			<string>is.workflow.actions.getvalueforkey</string>
			<key>WFWorkflowActionParameters</key>
			<dict>
				<key>CustomOutputName</key>
				<string>True</string>
				<key>UUID</key>
				<string>75B3E833-F1A7-4F63-A1C9-B6A6AE53F0FD</string>
				<key>WFDictionaryKey</key>
				<string>true</string>
				<key>WFInput</key>
				<dict>
					<key>Value</key>
					<dict>
						<key>OutputName</key>
						<string>Dictionary</string>
						<key>OutputUUID</key>
						<string>189935CB-6A0B-41B7-9E24-5CC90C717D96</string>
						<key>Type</key>
						<string>ActionOutput</string>
					</dict>
					<key>WFSerializationType</key>
					<string>WFTextTokenAttachment</string>
				</dict>
			</dict>
		</dict>
		<dict>
			<key>WFWorkflowActionIdentifier</key>
			<string>is.workflow.actions.setvariable</string>
			<key>WFWorkflowActionParameters</key>
			<dict>
				<key>WFInput</key>
				<dict>
					<key>Value</key>
					<dict>
						<key>Aggrandizements</key>
						<array>
							<dict>
								<key>CoercionItemClass</key>
								<string>WFBooleanContentItem</string>
								<key>Type</key>
								<string>WFCoercionVariableAggrandizement</string>
							</dict>
						</array>
						<key>OutputName</key>
						<string>True</string>
						<key>OutputUUID</key>
						<string>75B3E833-F1A7-4F63-A1C9-B6A6AE53F0FD</string>
						<key>Type</key>
						<string>ActionOutput</string>
					</dict>
					<key>WFSerializationType</key>
					<string>WFTextTokenAttachment</string>
				</dict>
				<key>WFVariableName</key>
				<string>True</string>
			</dict>
		</dict>
		<dict>
			<key>WFWorkflowActionIdentifier</key>
			<string>is.workflow.actions.setvariable</string>
			<key>WFWorkflowActionParameters</key>
			<dict>
				<key>WFInput</key>
				<dict>
					<key>Value</key>
					<dict>
						<key>Aggrandizements</key>
						<array>
							<dict>
								<key>CoercionItemClass</key>
								<string>WFBooleanContentItem</string>
								<key>Type</key>
								<string>WFCoercionVariableAggrandizement</string>
							</dict>
						</array>
						<key>Type</key>
						<string>Variable</string>
						<key>VariableName</key>
						<string>True</string>
					</dict>
					<key>WFSerializationType</key>
					<string>WFTextTokenAttachment</string>
				</dict>
				<key>WFVariableName</key>
				<string>Rollback</string>
			</dict>
		</dict>
		<dict>
			<key>WFWorkflowActionIdentifier</key>
			<string>is.workflow.actions.getvalueforkey</string>
			<key>WFWorkflowActionParameters</key>
			<dict>
				<key>CustomOutputName</key>
				<string>False</string>
				<key>UUID</key>
				<string>34A22C9F-D7A0-4C96-B38A-A6ADC54E27BC</string>
				<key>WFDictionaryKey</key>
				<string>false</string>
				<key>WFInput</key>
				<dict>
					<key>Value</key>
					<dict>
						<key>OutputName</key>
						<string>Dictionary</string>
						<key>OutputUUID</key>
						<string>189935CB-6A0B-41B7-9E24-5CC90C717D96</string>
						<key>Type</key>
						<string>ActionOutput</string>
					</dict>
					<key>WFSerializationType</key>
					<string>WFTextTokenAttachment</string>
				</dict>
			</dict>
		</dict>
		<dict>
			<key>WFWorkflowActionIdentifier</key>
			<string>is.workflow.actions.setvariable</string>
			<key>WFWorkflowActionParameters</key>
			<dict>
				<key>WFInput</key>
				<dict>
					<key>Value</key>
					<dict>
						<key>Aggrandizements</key>
						<array>
							<dict>
								<key>CoercionItemClass</key>
								<string>WFBooleanContentItem</string>
								<key>Type</key>
								<string>WFCoercionVariableAggrandizement</string>
							</dict>
						</array>
						<key>OutputName</key>
						<string>False</string>
						<key>OutputUUID</key>
						<string>34A22C9F-D7A0-4C96-B38A-A6ADC54E27BC</string>
						<key>Type</key>
						<string>ActionOutput</string>
					</dict>
					<key>WFSerializationType</key>
					<string>WFTextTokenAttachment</string>
				</dict>
				<key>WFVariableName</key>
				<string>False</string>
			</dict>
		</dict>
		<dict>
			<key>WFWorkflowActionIdentifier</key>
			<string>is.workflow.actions.comment</string>
			<key>WFWorkflowActionParameters</key>
			<dict>
				<key>WFCommentActionText</key>
				<string>



</string>
			</dict>
		</dict>
		<dict>
			<key>WFWorkflowActionIdentifier</key>
			<string>is.workflow.actions.url</string>
			<key>WFWorkflowActionParameters</key>
			<dict>
				<key>CustomOutputName</key>
				<string>Bustl. Update API</string>
				<key>Show-WFURLActionURL</key>
				<true/>
				<key>UUID</key>
				<string>4B72E54B-7CC0-4F1C-815A-E9408C8F29A9</string>
				<key>WFURLActionURL</key>
				<dict>
					<key>Value</key>
					<dict>
						<key>attachmentsByRange</key>
						<dict>
							<key>{46, 1}</key>
							<dict>
								<key>OutputName</key>
								<string>AUUID</string>
								<key>OutputUUID</key>
								<string>0BE0E935-AD3C-405F-86DA-841E8601E544</string>
								<key>Type</key>
								<string>ActionOutput</string>
							</dict>
						</dict>
						<key>string</key>
						<string>https://Cutz.Bustl.io/library/versions/latest/￼.json</string>
					</dict>
					<key>WFSerializationType</key>
					<string>WFTextTokenString</string>
				</dict>
			</dict>
		</dict>
		<dict>
			<key>WFWorkflowActionIdentifier</key>
			<string>is.workflow.actions.gettypeaction</string>
			<key>WFWorkflowActionParameters</key>
			<dict>
				<key>CustomOutputName</key>
				<string>Response</string>
				<key>UUID</key>
				<string>D0DCFA36-D503-40FB-A621-550838259A63</string>
				<key>WFFileType</key>
				<string>public.json</string>
				<key>WFInput</key>
				<dict>
					<key>Value</key>
					<dict>
						<key>OutputName</key>
						<string>Bustl. Update API</string>
						<key>OutputUUID</key>
						<string>4B72E54B-7CC0-4F1C-815A-E9408C8F29A9</string>
						<key>Type</key>
						<string>ActionOutput</string>
					</dict>
					<key>WFSerializationType</key>
					<string>WFTextTokenAttachment</string>
				</dict>
			</dict>
		</dict>
		<dict>
			<key>WFWorkflowActionIdentifier</key>
			<string>is.workflow.actions.detect.dictionary</string>
			<key>WFWorkflowActionParameters</key>
			<dict>
				<key>UUID</key>
				<string>EE0777FB-9815-49C1-99E9-63ECF1460794</string>
				<key>WFInput</key>
				<dict>
					<key>Value</key>
					<dict>
						<key>OutputName</key>
						<string>Response</string>
						<key>OutputUUID</key>
						<string>D0DCFA36-D503-40FB-A621-550838259A63</string>
						<key>Type</key>
						<string>ActionOutput</string>
					</dict>
					<key>WFSerializationType</key>
					<string>WFTextTokenAttachment</string>
				</dict>
			</dict>
		</dict>
		<dict>
			<key>WFWorkflowActionIdentifier</key>
			<string>is.workflow.actions.setvariable</string>
			<key>WFWorkflowActionParameters</key>
			<dict>
				<key>WFInput</key>
				<dict>
					<key>Value</key>
					<dict>
						<key>OutputName</key>
						<string>Dictionary</string>
						<key>OutputUUID</key>
						<string>EE0777FB-9815-49C1-99E9-63ECF1460794</string>
						<key>Type</key>
						<string>ActionOutput</string>
					</dict>
					<key>WFSerializationType</key>
					<string>WFTextTokenAttachment</string>
				</dict>
				<key>WFVariableName</key>
				<string>Response</string>
			</dict>
		</dict>
		<dict>
			<key>WFWorkflowActionIdentifier</key>
			<string>is.workflow.actions.detect.text</string>
			<key>WFWorkflowActionParameters</key>
			<dict>
				<key>CustomOutputName</key>
				<string>Latest</string>
				<key>UUID</key>
				<string>CD970545-F8C5-4AAE-A70B-EDDE45B02349</string>
				<key>WFInput</key>
				<dict>
					<key>Value</key>
					<dict>
						<key>Aggrandizements</key>
						<array>
							<dict>
								<key>DictionaryKey</key>
								<string>version</string>
								<key>Type</key>
								<string>WFDictionaryValueVariableAggrandizement</string>
							</dict>
						</array>
						<key>Type</key>
						<string>Variable</string>
						<key>VariableName</key>
						<string>Response</string>
					</dict>
					<key>WFSerializationType</key>
					<string>WFTextTokenAttachment</string>
				</dict>
			</dict>
		</dict>
		<dict>
			<key>WFWorkflowActionIdentifier</key>
			<string>is.workflow.actions.setvariable</string>
			<key>WFWorkflowActionParameters</key>
			<dict>
				<key>WFInput</key>
				<dict>
					<key>Value</key>
					<dict>
						<key>OutputName</key>
						<string>Latest</string>
						<key>OutputUUID</key>
						<string>CD970545-F8C5-4AAE-A70B-EDDE45B02349</string>
						<key>Type</key>
						<string>ActionOutput</string>
					</dict>
					<key>WFSerializationType</key>
					<string>WFTextTokenAttachment</string>
				</dict>
				<key>WFVariableName</key>
				<string>Latest</string>
			</dict>
		</dict>
		<dict>
			<key>WFWorkflowActionIdentifier</key>
			<string>is.workflow.actions.comment</string>
			<key>WFWorkflowActionParameters</key>
			<dict>
				<key>WFCommentActionText</key>
				<string>



</string>
			</dict>
		</dict>
		<dict>
			<key>WFWorkflowActionIdentifier</key>
			<string>is.workflow.actions.gettext</string>
			<key>WFWorkflowActionParameters</key>
			<dict>
				<key>CustomOutputName</key>
				<string>Script</string>
				<key>UUID</key>
				<string>EFF6107E-A61E-43D1-AF30-B5C6F3845D0B</string>
				<key>WFTextActionText</key>
				<dict>
					<key>Value</key>
					<dict>
						<key>attachmentsByRange</key>
						<dict>
							<key>{251, 1}</key>
							<dict>
								<key>Aggrandizements</key>
								<array>
									<dict>
										<key>CoercionItemClass</key>
										<string>WFBooleanContentItem</string>
										<key>Type</key>
										<string>WFCoercionVariableAggrandizement</string>
									</dict>
								</array>
								<key>Type</key>
								<string>Variable</string>
								<key>VariableName</key>
								<string>True</string>
							</dict>
							<key>{276, 1}</key>
							<dict>
								<key>Aggrandizements</key>
								<array>
									<dict>
										<key>CoercionItemClass</key>
										<string>WFBooleanContentItem</string>
										<key>Type</key>
										<string>WFCoercionVariableAggrandizement</string>
									</dict>
								</array>
								<key>Type</key>
								<string>Variable</string>
								<key>VariableName</key>
								<string>False</string>
							</dict>
							<key>{302, 1}</key>
							<dict>
								<key>Aggrandizements</key>
								<array>
									<dict>
										<key>CoercionItemClass</key>
										<string>WFBooleanContentItem</string>
										<key>Type</key>
										<string>WFCoercionVariableAggrandizement</string>
									</dict>
								</array>
								<key>Type</key>
								<string>Variable</string>
								<key>VariableName</key>
								<string>False</string>
							</dict>
							<key>{314, 1}</key>
							<dict>
								<key>Aggrandizements</key>
								<array>
									<dict>
										<key>CoercionItemClass</key>
										<string>WFBooleanContentItem</string>
										<key>Type</key>
										<string>WFCoercionVariableAggrandizement</string>
									</dict>
								</array>
								<key>Type</key>
								<string>Variable</string>
								<key>VariableName</key>
								<string>True</string>
							</dict>
							<key>{344, 1}</key>
							<dict>
								<key>Type</key>
								<string>Variable</string>
								<key>VariableName</key>
								<string>Current</string>
							</dict>
							<key>{354, 1}</key>
							<dict>
								<key>Type</key>
								<string>Variable</string>
								<key>VariableName</key>
								<string>Latest</string>
							</dict>
						</dict>
						<key>string</key>
						<string>&lt;script&gt;
function cmp (a, b) {
let pa = a.split('.');
let pb = b.split('.');
for (let i = 0; i &lt; Math.max(pa.length, pb.length); i++) {
let na = Number(pa[i]);
let nb = Number(pb[i]);
if (isNaN(na)) na = 0;
if (isNaN(nb)) nb = 0;
if (na &gt; nb) return "￼";
if (nb &gt; na) return "￼";
}
if (a != b) return "￼";
return "￼";
};
let data = {"current":"￼","new":"￼"};
document.write(cmp(data.current, data.new));
&lt;/script&gt;</string>
					</dict>
					<key>WFSerializationType</key>
					<string>WFTextTokenString</string>
				</dict>
			</dict>
		</dict>
		<dict>
			<key>WFWorkflowActionIdentifier</key>
			<string>is.workflow.actions.url</string>
			<key>WFWorkflowActionParameters</key>
			<dict>
				<key>Show-WFURLActionURL</key>
				<true/>
				<key>UUID</key>
				<string>4ECCCFCF-E96F-4340-A5FE-E90A17573A01</string>
				<key>WFURLActionURL</key>
				<dict>
					<key>Value</key>
					<dict>
						<key>attachmentsByRange</key>
						<dict>
							<key>{29, 1}</key>
							<dict>
								<key>OutputName</key>
								<string>Script</string>
								<key>OutputUUID</key>
								<string>EFF6107E-A61E-43D1-AF30-B5C6F3845D0B</string>
								<key>Type</key>
								<string>ActionOutput</string>
							</dict>
						</dict>
						<key>string</key>
						<string>data:text/html;charset=utf-8,￼</string>
					</dict>
					<key>WFSerializationType</key>
					<string>WFTextTokenString</string>
				</dict>
			</dict>
		</dict>
		<dict>
			<key>WFWorkflowActionIdentifier</key>
			<string>is.workflow.actions.gettypeaction</string>
			<key>WFWorkflowActionParameters</key>
			<dict>
				<key>CustomOutputName</key>
				<string>Output</string>
				<key>UUID</key>
				<string>3A6213D1-4657-4F8C-9D6D-B69DC8A4F20E</string>
				<key>WFFileType</key>
				<string>com.apple.webarchive</string>
				<key>WFInput</key>
				<dict>
					<key>Value</key>
					<dict>
						<key>OutputName</key>
						<string>URL</string>
						<key>OutputUUID</key>
						<string>4ECCCFCF-E96F-4340-A5FE-E90A17573A01</string>
						<key>Type</key>
						<string>ActionOutput</string>
					</dict>
					<key>WFSerializationType</key>
					<string>WFTextTokenAttachment</string>
				</dict>
			</dict>
		</dict>
		<dict>
			<key>WFWorkflowActionIdentifier</key>
			<string>is.workflow.actions.detect.text</string>
			<key>WFWorkflowActionParameters</key>
			<dict>
				<key>CustomOutputName</key>
				<string>Check</string>
				<key>UUID</key>
				<string>CA4AE2CF-301F-4132-9E9E-F29CA24345FC</string>
				<key>WFInput</key>
				<dict>
					<key>Value</key>
					<dict>
						<key>Aggrandizements</key>
						<array>
							<dict>
								<key>CoercionItemClass</key>
								<string>WFStringContentItem</string>
								<key>Type</key>
								<string>WFCoercionVariableAggrandizement</string>
							</dict>
						</array>
						<key>OutputName</key>
						<string>Output</string>
						<key>OutputUUID</key>
						<string>3A6213D1-4657-4F8C-9D6D-B69DC8A4F20E</string>
						<key>Type</key>
						<string>ActionOutput</string>
					</dict>
					<key>WFSerializationType</key>
					<string>WFTextTokenAttachment</string>
				</dict>
			</dict>
		</dict>
		<dict>
			<key>WFWorkflowActionIdentifier</key>
			<string>is.workflow.actions.setvariable</string>
			<key>WFWorkflowActionParameters</key>
			<dict>
				<key>WFInput</key>
				<dict>
					<key>Value</key>
					<dict>
						<key>Aggrandizements</key>
						<array>
							<dict>
								<key>CoercionItemClass</key>
								<string>WFBooleanContentItem</string>
								<key>Type</key>
								<string>WFCoercionVariableAggrandizement</string>
							</dict>
						</array>
						<key>OutputName</key>
						<string>Check</string>
						<key>OutputUUID</key>
						<string>CA4AE2CF-301F-4132-9E9E-F29CA24345FC</string>
						<key>Type</key>
						<string>ActionOutput</string>
					</dict>
					<key>WFSerializationType</key>
					<string>WFTextTokenAttachment</string>
				</dict>
				<key>WFVariableName</key>
				<string>Up To Date</string>
			</dict>
		</dict>
		<dict>
			<key>WFWorkflowActionIdentifier</key>
			<string>is.workflow.actions.conditional</string>
			<key>WFWorkflowActionParameters</key>
			<dict>
				<key>GroupingIdentifier</key>
				<string>AFD64663-0539-4E83-9A03-DB028C30E14C</string>
				<key>WFCondition</key>
				<integer>4</integer>
				<key>WFConditionalActionString</key>
				<string>up</string>
				<key>WFControlFlowMode</key>
				<integer>0</integer>
				<key>WFInput</key>
				<dict>
					<key>Type</key>
					<string>Variable</string>
					<key>Variable</key>
					<dict>
						<key>Value</key>
						<dict>
							<key>Aggrandizements</key>
							<array>
								<dict>
									<key>CoercionItemClass</key>
									<string>WFBooleanContentItem</string>
									<key>Type</key>
									<string>WFCoercionVariableAggrandizement</string>
								</dict>
							</array>
							<key>Type</key>
							<string>Variable</string>
							<key>VariableName</key>
							<string>Up To Date</string>
						</dict>
						<key>WFSerializationType</key>
						<string>WFTextTokenAttachment</string>
					</dict>
				</dict>
			</dict>
		</dict>
		<dict>
			<key>WFWorkflowActionIdentifier</key>
			<string>is.workflow.actions.conditional</string>
			<key>WFWorkflowActionParameters</key>
			<dict>
				<key>GroupingIdentifier</key>
				<string>2805C904-3543-44E8-A6CA-2091FAB7CC46</string>
				<key>WFCondition</key>
				<integer>4</integer>
				<key>WFConditionalActionString</key>
				<string>Bustl. Updater</string>
				<key>WFControlFlowMode</key>
				<integer>0</integer>
				<key>WFInput</key>
				<dict>
					<key>Type</key>
					<string>Variable</string>
					<key>Variable</key>
					<dict>
						<key>Value</key>
						<dict>
							<key>Aggrandizements</key>
							<array>
								<dict>
									<key>CoercionItemClass</key>
									<string>WFBooleanContentItem</string>
									<key>Type</key>
									<string>WFCoercionVariableAggrandizement</string>
								</dict>
							</array>
							<key>OutputName</key>
							<string>Quiet</string>
							<key>OutputUUID</key>
							<string>6EAA2F70-92AA-4146-80DA-E70C4FB84500</string>
							<key>Type</key>
							<string>ActionOutput</string>
						</dict>
						<key>WFSerializationType</key>
						<string>WFTextTokenAttachment</string>
					</dict>
				</dict>
			</dict>
		</dict>
		<dict>
			<key>WFWorkflowActionIdentifier</key>
			<string>is.workflow.actions.output</string>
			<key>WFWorkflowActionParameters</key>
			<dict>
				<key>UUID</key>
				<string>364833E5-B2FA-4C2A-B85C-DB41E3078570</string>
				<key>WFOutput</key>
				<dict>
					<key>Value</key>
					<dict>
						<key>attachmentsByRange</key>
						<dict>
							<key>{0, 1}</key>
							<dict>
								<key>Aggrandizements</key>
								<array>
									<dict>
										<key>CoercionItemClass</key>
										<string>WFBooleanContentItem</string>
										<key>Type</key>
										<string>WFCoercionVariableAggrandizement</string>
									</dict>
								</array>
								<key>Type</key>
								<string>Variable</string>
								<key>VariableName</key>
								<string>Up To Date</string>
							</dict>
						</dict>
						<key>string</key>
						<string>￼</string>
					</dict>
					<key>WFSerializationType</key>
					<string>WFTextTokenString</string>
				</dict>
			</dict>
		</dict>
		<dict>
			<key>WFWorkflowActionIdentifier</key>
			<string>is.workflow.actions.conditional</string>
			<key>WFWorkflowActionParameters</key>
			<dict>
				<key>GroupingIdentifier</key>
				<string>2805C904-3543-44E8-A6CA-2091FAB7CC46</string>
				<key>UUID</key>
				<string>0FDFE5FD-4079-481F-93AE-1CDA514C9CDF</string>
				<key>WFControlFlowMode</key>
				<integer>2</integer>
			</dict>
		</dict>
		<dict>
			<key>WFWorkflowActionIdentifier</key>
			<string>is.workflow.actions.conditional</string>
			<key>WFWorkflowActionParameters</key>
			<dict>
				<key>GroupingIdentifier</key>
				<string>AFD64663-0539-4E83-9A03-DB028C30E14C</string>
				<key>WFControlFlowMode</key>
				<integer>1</integer>
			</dict>
		</dict>
		<dict>
			<key>WFWorkflowActionIdentifier</key>
			<string>is.workflow.actions.conditional</string>
			<key>WFWorkflowActionParameters</key>
			<dict>
				<key>GroupingIdentifier</key>
				<string>AFD64663-0539-4E83-9A03-DB028C30E14C</string>
				<key>UUID</key>
				<string>7F456F27-A4B0-4F34-A0B6-0A70AA705AD5</string>
				<key>WFControlFlowMode</key>
				<integer>2</integer>
			</dict>
		</dict>
		<dict>
			<key>WFWorkflowActionIdentifier</key>
			<string>is.workflow.actions.comment</string>
			<key>WFWorkflowActionParameters</key>
			<dict>
				<key>WFCommentActionText</key>
				<string>



</string>
			</dict>
		</dict>
		<dict>
			<key>WFWorkflowActionIdentifier</key>
			<string>is.workflow.actions.detect.text</string>
			<key>WFWorkflowActionParameters</key>
			<dict>
				<key>CustomOutputName</key>
				<string>Description</string>
				<key>UUID</key>
				<string>9321159E-86E2-4803-949C-C9A4CDF5AE06</string>
				<key>WFInput</key>
				<dict>
					<key>Value</key>
					<dict>
						<key>Aggrandizements</key>
						<array>
							<dict>
								<key>DictionaryKey</key>
								<string>description</string>
								<key>Type</key>
								<string>WFDictionaryValueVariableAggrandizement</string>
							</dict>
						</array>
						<key>Type</key>
						<string>Variable</string>
						<key>VariableName</key>
						<string>Response</string>
					</dict>
					<key>WFSerializationType</key>
					<string>WFTextTokenAttachment</string>
				</dict>
			</dict>
		</dict>
		<dict>
			<key>WFWorkflowActionIdentifier</key>
			<string>is.workflow.actions.detect.date</string>
			<key>WFWorkflowActionParameters</key>
			<dict>
				<key>CustomOutputName</key>
				<string>Published</string>
				<key>UUID</key>
				<string>626EE94D-D2FF-41F3-AED9-AEBFBFDE886F</string>
				<key>WFInput</key>
				<dict>
					<key>Value</key>
					<dict>
						<key>Aggrandizements</key>
						<array>
							<dict>
								<key>CoercionItemClass</key>
								<string>WFDictionaryContentItem</string>
								<key>Type</key>
								<string>WFCoercionVariableAggrandizement</string>
							</dict>
							<dict>
								<key>DictionaryKey</key>
								<string>release</string>
								<key>Type</key>
								<string>WFDictionaryValueVariableAggrandizement</string>
							</dict>
						</array>
						<key>Type</key>
						<string>Variable</string>
						<key>VariableName</key>
						<string>Response</string>
					</dict>
					<key>WFSerializationType</key>
					<string>WFTextTokenAttachment</string>
				</dict>
			</dict>
		</dict>
		<dict>
			<key>WFWorkflowActionIdentifier</key>
			<string>is.workflow.actions.text.split</string>
			<key>WFWorkflowActionParameters</key>
			<dict>
				<key>Show-text</key>
				<true/>
				<key>UUID</key>
				<string>1CFBB93C-B37D-47D7-B604-81275A24EB94</string>
				<key>WFTextCustomSeparator</key>
				<string>\n</string>
				<key>WFTextSeparator</key>
				<string>New Lines</string>
				<key>text</key>
				<dict>
					<key>Value</key>
					<dict>
						<key>Aggrandizements</key>
						<array>
							<dict>
								<key>CoercionItemClass</key>
								<string>WFDictionaryContentItem</string>
								<key>Type</key>
								<string>WFCoercionVariableAggrandizement</string>
							</dict>
							<dict>
								<key>DictionaryKey</key>
								<string>notes</string>
								<key>Type</key>
								<string>WFDictionaryValueVariableAggrandizement</string>
							</dict>
						</array>
						<key>Type</key>
						<string>Variable</string>
						<key>VariableName</key>
						<string>Response</string>
					</dict>
					<key>WFSerializationType</key>
					<string>WFTextTokenAttachment</string>
				</dict>
			</dict>
		</dict>
		<dict>
			<key>WFWorkflowActionIdentifier</key>
			<string>is.workflow.actions.text.combine</string>
			<key>WFWorkflowActionParameters</key>
			<dict>
				<key>CustomOutputName</key>
				<string>Release Notes</string>
				<key>Show-text</key>
				<true/>
				<key>UUID</key>
				<string>B5B05A26-CA2D-43B0-913F-7625FEAF1820</string>
				<key>WFTextCustomSeparator</key>
				<string>&lt;br /&gt;— </string>
				<key>WFTextSeparator</key>
				<string>Custom</string>
				<key>text</key>
				<dict>
					<key>Value</key>
					<dict>
						<key>OutputName</key>
						<string>Split Text</string>
						<key>OutputUUID</key>
						<string>1CFBB93C-B37D-47D7-B604-81275A24EB94</string>
						<key>Type</key>
						<string>ActionOutput</string>
					</dict>
					<key>WFSerializationType</key>
					<string>WFTextTokenAttachment</string>
				</dict>
			</dict>
		</dict>
		<dict>
			<key>WFWorkflowActionIdentifier</key>
			<string>is.workflow.actions.text.replace</string>
			<key>WFWorkflowActionParameters</key>
			<dict>
				<key>CustomOutputName</key>
				<string>Download</string>
				<key>UUID</key>
				<string>BEDD3813-62F8-408A-A8F1-9994B836055B</string>
				<key>WFInput</key>
				<dict>
					<key>Value</key>
					<dict>
						<key>attachmentsByRange</key>
						<dict>
							<key>{0, 1}</key>
							<dict>
								<key>Aggrandizements</key>
								<array>
									<dict>
										<key>CoercionItemClass</key>
										<string>WFDictionaryContentItem</string>
										<key>Type</key>
										<string>WFCoercionVariableAggrandizement</string>
									</dict>
									<dict>
										<key>DictionaryKey</key>
										<string>link</string>
										<key>Type</key>
										<string>WFDictionaryValueVariableAggrandizement</string>
									</dict>
								</array>
								<key>Type</key>
								<string>Variable</string>
								<key>VariableName</key>
								<string>Response</string>
							</dict>
						</dict>
						<key>string</key>
						<string>￼</string>
					</dict>
					<key>WFSerializationType</key>
					<string>WFTextTokenString</string>
				</dict>
				<key>WFReplaceTextFind</key>
				<string>^.+?(?=\/shortcut)</string>
				<key>WFReplaceTextRegularExpression</key>
				<true/>
				<key>WFReplaceTextReplace</key>
				<string>shortcuts:/</string>
			</dict>
		</dict>
		<dict>
			<key>WFWorkflowActionIdentifier</key>
			<string>is.workflow.actions.detect.link</string>
			<key>WFWorkflowActionParameters</key>
			<dict>
				<key>CustomOutputName</key>
				<string>Icon URL</string>
				<key>UUID</key>
				<string>DBF5B298-9B6F-4007-B18F-945764E753B4</string>
				<key>WFInput</key>
				<dict>
					<key>Value</key>
					<dict>
						<key>attachmentsByRange</key>
						<dict>
							<key>{0, 1}</key>
							<dict>
								<key>Aggrandizements</key>
								<array>
									<dict>
										<key>DictionaryKey</key>
										<string>icon</string>
										<key>Type</key>
										<string>WFDictionaryValueVariableAggrandizement</string>
									</dict>
								</array>
								<key>Type</key>
								<string>Variable</string>
								<key>VariableName</key>
								<string>Response</string>
							</dict>
						</dict>
						<key>string</key>
						<string>￼</string>
					</dict>
					<key>WFSerializationType</key>
					<string>WFTextTokenString</string>
				</dict>
			</dict>
		</dict>
		<dict>
			<key>WFWorkflowActionIdentifier</key>
			<string>is.workflow.actions.detect.text</string>
			<key>WFWorkflowActionParameters</key>
			<dict>
				<key>CustomOutputName</key>
				<string>Color</string>
				<key>UUID</key>
				<string>A302248C-DEA4-48EB-BE5F-B9C5AEFE2233</string>
				<key>WFInput</key>
				<dict>
					<key>Value</key>
					<dict>
						<key>Aggrandizements</key>
						<array>
							<dict>
								<key>DictionaryKey</key>
								<string>color</string>
								<key>Type</key>
								<string>WFDictionaryValueVariableAggrandizement</string>
							</dict>
						</array>
						<key>Type</key>
						<string>Variable</string>
						<key>VariableName</key>
						<string>Response</string>
					</dict>
					<key>WFSerializationType</key>
					<string>WFTextTokenAttachment</string>
				</dict>
			</dict>
		</dict>
		<dict>
			<key>WFWorkflowActionIdentifier</key>
			<string>is.workflow.actions.comment</string>
			<key>WFWorkflowActionParameters</key>
			<dict>
				<key>WFCommentActionText</key>
				<string>



</string>
			</dict>
		</dict>
		<dict>
			<key>WFWorkflowActionIdentifier</key>
			<string>is.workflow.actions.gettext</string>
			<key>WFWorkflowActionParameters</key>
			<dict>
				<key>CustomOutputName</key>
				<string>Head</string>
				<key>UUID</key>
				<string>ECF13BBC-2EB7-442F-BABC-7902A9144658</string>
				<key>WFTextActionText</key>
				<dict>
					<key>Value</key>
					<dict>
						<key>attachmentsByRange</key>
						<dict>
							<key>{1328, 1}</key>
							<dict>
								<key>OutputName</key>
								<string>Color</string>
								<key>OutputUUID</key>
								<string>A302248C-DEA4-48EB-BE5F-B9C5AEFE2233</string>
								<key>Type</key>
								<string>ActionOutput</string>
							</dict>
							<key>{1492, 1}</key>
							<dict>
								<key>OutputName</key>
								<string>Color</string>
								<key>OutputUUID</key>
								<string>A302248C-DEA4-48EB-BE5F-B9C5AEFE2233</string>
								<key>Type</key>
								<string>ActionOutput</string>
							</dict>
							<key>{201, 1}</key>
							<dict>
								<key>OutputName</key>
								<string>Name</string>
								<key>OutputUUID</key>
								<string>AD02644F-B0C7-4059-B2B4-EB950B8B834E</string>
								<key>Type</key>
								<string>ActionOutput</string>
							</dict>
							<key>{2105, 1}</key>
							<dict>
								<key>OutputName</key>
								<string>Color</string>
								<key>OutputUUID</key>
								<string>A302248C-DEA4-48EB-BE5F-B9C5AEFE2233</string>
								<key>Type</key>
								<string>ActionOutput</string>
							</dict>
							<key>{3082, 1}</key>
							<dict>
								<key>OutputName</key>
								<string>Color</string>
								<key>OutputUUID</key>
								<string>A302248C-DEA4-48EB-BE5F-B9C5AEFE2233</string>
								<key>Type</key>
								<string>ActionOutput</string>
							</dict>
							<key>{3128, 1}</key>
							<dict>
								<key>OutputName</key>
								<string>Icon URL</string>
								<key>OutputUUID</key>
								<string>DBF5B298-9B6F-4007-B18F-945764E753B4</string>
								<key>Type</key>
								<string>ActionOutput</string>
							</dict>
							<key>{3202, 1}</key>
							<dict>
								<key>OutputName</key>
								<string>Name</string>
								<key>OutputUUID</key>
								<string>AD02644F-B0C7-4059-B2B4-EB950B8B834E</string>
								<key>Type</key>
								<string>ActionOutput</string>
							</dict>
							<key>{3283, 1}</key>
							<dict>
								<key>OutputName</key>
								<string>Description</string>
								<key>OutputUUID</key>
								<string>9321159E-86E2-4803-949C-C9A4CDF5AE06</string>
								<key>Type</key>
								<string>ActionOutput</string>
							</dict>
						</dict>
						<key>string</key>
						<string>&lt;!----&gt;
&lt;!--Bustl.•io Shortcut Updater--&gt;
&lt;!----&gt;
&lt;!DOCTYPE html&gt;
&lt;html&gt;
  &lt;head&gt;
    &lt;meta name="viewport" content="width=device-width, initial-scale=1"&gt;
    &lt;meta charset="utf-8"&gt;
&lt;!----&gt;
    &lt;title&gt;￼  |  Bustl.•io Updater&lt;/title&gt;
&lt;!----&gt;
    &lt;style&gt;
      body {
        padding: 0px;
        margin: 0;
        font-family: Verdana;
        background-color: #FFFEFF;
      }
      h2 {
        font-size:30px;
        margin-top: 5px;
      }
      h1 { 
        text-align: center;
      }
      p, h3 {
        margin-left: 15px;
        margin-right: 15px;
      }
      img {
        width: 40px;
        height: 40px;
        position: relative;
        margin-right: 5px;
        margin-top: 5px;
        margin-left: 5px;
        margin-bottom: 5px;
      }
      .description {
        font-family: Verdana;
        margin-top: -20px;
        margin-left: 90px;
        margin-right: 1em;
        margin-bottom: 15px;
      }
      .credit {
        text-align: right;
        font-size: 20px;
        font-family: Verdana;
        margin-right: 1em;
        margin-top: 7px;
        margin-bottom: 7px;
        font-style: italic;
        color: black;
      }
      .foot {
         border: 1px solid black;
         padding: 5px;
         border-radius: 5px;
/* Shortcut Icon Color */
         background-color: ￼;
      }
      .head {
         border: 1px solid white;
         padding: 5px;
         border-radius: 5px;
/* Shortcut Icon Color */
         background-color: ￼;
      }
      .grid {
        display: grid; 
        grid-template-columns: 1fr 4fr;
        margin: 5px;
      }
      .update {
        background-color: blue;
        text-decoration: none;
        border-radius: 5px;
        border: 1px solid white;
        color: white;
        font-size: 25px;
        font-weight: bold;
        padding: 5px;
        padding-left: 10px;
        padding-right: 10px;
        margin-left: 5px;
        margin-right: 5px;
      }
      .link {
        text-decoration: none;
        color: black;
      }
      .card {
/* Shortcut Icon Color */
        background-color: ￼;
        border: 5px solid #FFFEFF; 
        border-radius: 5px;
      }
      .button {
        background-color: black;
        text-decoration: none;
        border-radius: 5px;
        border: 1px solid white;
        color: white;
        font-size: 15px;
        font-weight: bold;
        padding: 5px;
        padding-left: 10px;
        padding-right: 10px;
        margin-left: 5px;
        margin-right: 5px;
      }
      @media (prefers-color-scheme: dark) {
        body {
          background-color: #1C1C1E;
          color: #AAAAAA;
        }
        p {
          color: #AAAAAA;
        }
        h1,h3 {
          color: white;
        }
        h2,.description,.button,.credit {
          color: white;
          border-color: black;
        }
        .button {
          background-color: white;
        }
      }
    &lt;/style&gt;
  &lt;/head&gt;
  &lt;body&gt;
&lt;!----&gt;
    &lt;div class="head"&gt;
      &lt;div class="card"&gt;
        &lt;div class="grid" style="background-color: ￼;"&gt;
&lt;!--Shortcut Icon--&gt;
          &lt;img src="￼" style="width: 70px; height: 70px;"&gt;
&lt;!--Shortcut Name--&gt;
          &lt;h2&gt;￼&lt;/h2&gt;
        &lt;/div&gt;
&lt;!--Shortcut Description--&gt;
        &lt;p class="description"&gt;￼.&lt;/p&gt;
      &lt;/div&gt;
    &lt;/div&gt;</string>
					</dict>
					<key>WFSerializationType</key>
					<string>WFTextTokenString</string>
				</dict>
			</dict>
		</dict>
		<dict>
			<key>WFWorkflowActionIdentifier</key>
			<string>is.workflow.actions.conditional</string>
			<key>WFWorkflowActionParameters</key>
			<dict>
				<key>GroupingIdentifier</key>
				<string>E71087D4-423E-4A13-A5AB-BCDEB8F169B5</string>
				<key>WFCondition</key>
				<integer>4</integer>
				<key>WFConditionalActionString</key>
				<dict>
					<key>Value</key>
					<dict>
						<key>attachmentsByRange</key>
						<dict>
							<key>{0, 1}</key>
							<dict>
								<key>Aggrandizements</key>
								<array>
									<dict>
										<key>CoercionItemClass</key>
										<string>WFStringContentItem</string>
										<key>Type</key>
										<string>WFCoercionVariableAggrandizement</string>
									</dict>
								</array>
								<key>OutputName</key>
								<string>Latest</string>
								<key>OutputUUID</key>
								<string>148DB66A-D9EF-4C19-84D3-26409B287388</string>
								<key>Type</key>
								<string>ActionOutput</string>
							</dict>
						</dict>
						<key>string</key>
						<string>￼</string>
					</dict>
					<key>WFSerializationType</key>
					<string>WFTextTokenString</string>
				</dict>
				<key>WFControlFlowMode</key>
				<integer>0</integer>
				<key>WFInput</key>
				<dict>
					<key>Type</key>
					<string>Variable</string>
					<key>Variable</key>
					<dict>
						<key>Value</key>
						<dict>
							<key>Aggrandizements</key>
							<array>
								<dict>
									<key>CoercionItemClass</key>
									<string>WFBooleanContentItem</string>
									<key>Type</key>
									<string>WFCoercionVariableAggrandizement</string>
								</dict>
							</array>
							<key>Type</key>
							<string>Variable</string>
							<key>VariableName</key>
							<string>Up To Date</string>
						</dict>
						<key>WFSerializationType</key>
						<string>WFTextTokenAttachment</string>
					</dict>
				</dict>
			</dict>
		</dict>
		<dict>
			<key>WFWorkflowActionIdentifier</key>
			<string>is.workflow.actions.gettext</string>
			<key>WFWorkflowActionParameters</key>
			<dict>
				<key>WFTextActionText</key>
				<dict>
					<key>Value</key>
					<dict>
						<key>attachmentsByRange</key>
						<dict>
							<key>{169, 1}</key>
							<dict>
								<key>OutputName</key>
								<string>Name</string>
								<key>OutputUUID</key>
								<string>AD02644F-B0C7-4059-B2B4-EB950B8B834E</string>
								<key>Type</key>
								<string>ActionOutput</string>
							</dict>
							<key>{172, 1}</key>
							<dict>
								<key>Aggrandizements</key>
								<array>
									<dict>
										<key>DictionaryKey</key>
										<string>version</string>
										<key>Type</key>
										<string>WFDictionaryValueVariableAggrandizement</string>
									</dict>
								</array>
								<key>Type</key>
								<string>Variable</string>
								<key>VariableName</key>
								<string>Response</string>
							</dict>
							<key>{190, 1}</key>
							<dict>
								<key>OutputName</key>
								<string>Published</string>
								<key>OutputUUID</key>
								<string>626EE94D-D2FF-41F3-AED9-AEBFBFDE886F</string>
								<key>Type</key>
								<string>ActionOutput</string>
							</dict>
							<key>{314, 1}</key>
							<dict>
								<key>OutputName</key>
								<string>Release Notes</string>
								<key>OutputUUID</key>
								<string>B5B05A26-CA2D-43B0-913F-7625FEAF1820</string>
								<key>Type</key>
								<string>ActionOutput</string>
							</dict>
						</dict>
						<key>string</key>
						<string>&lt;!--Up-To-Date--&gt; 
&lt;!----&gt;
      &lt;div&gt;&lt;center&gt;
        &lt;h1&gt;Up-To-Date&lt;/h1&gt;&lt;/center&gt;
        
&lt;!--Latest Version &amp; Release Date--&gt;
        &lt;p style="padding-left: 10px;"&gt;￼ v￼ was released on ￼.&lt;/p&gt;

&lt;!--Notes--&gt;
        &lt;p&gt;&lt;h3 style="padding-left: 10px;"&gt;Release Notes&lt;/h3&gt;
        &lt;p style="padding-left: 10px;"&gt;— ￼&lt;/p&gt;&lt;br /&gt;&lt;/p&gt;

&lt;!--Up-To-DATE--&gt; 
        &lt;strong&gt;&lt;p style="padding-left: 10px;"&gt;Press &lt;a onclick="window.open('shortcuts://'); window.close();"&gt;&lt;button class="button"&gt;DONE&lt;/button&gt;&lt;/a&gt; to continue.&lt;/p&gt;&lt;br /&gt;&lt;/strong&gt;
      &lt;/div&gt;
&lt;!----&gt;</string>
					</dict>
					<key>WFSerializationType</key>
					<string>WFTextTokenString</string>
				</dict>
			</dict>
		</dict>
		<dict>
			<key>WFWorkflowActionIdentifier</key>
			<string>is.workflow.actions.conditional</string>
			<key>WFWorkflowActionParameters</key>
			<dict>
				<key>GroupingIdentifier</key>
				<string>E71087D4-423E-4A13-A5AB-BCDEB8F169B5</string>
				<key>WFControlFlowMode</key>
				<integer>1</integer>
			</dict>
		</dict>
		<dict>
			<key>WFWorkflowActionIdentifier</key>
			<string>is.workflow.actions.gettext</string>
			<key>WFWorkflowActionParameters</key>
			<dict>
				<key>WFTextActionText</key>
				<dict>
					<key>Value</key>
					<dict>
						<key>attachmentsByRange</key>
						<dict>
							<key>{132, 1}</key>
							<dict>
								<key>Type</key>
								<string>Variable</string>
								<key>VariableName</key>
								<string>Current</string>
							</dict>
							<key>{135, 1}</key>
							<dict>
								<key>Type</key>
								<string>Variable</string>
								<key>VariableName</key>
								<string>Latest</string>
							</dict>
							<key>{240, 1}</key>
							<dict>
								<key>OutputName</key>
								<string>Name</string>
								<key>OutputUUID</key>
								<string>AD02644F-B0C7-4059-B2B4-EB950B8B834E</string>
								<key>Type</key>
								<string>ActionOutput</string>
							</dict>
							<key>{243, 1}</key>
							<dict>
								<key>Type</key>
								<string>Variable</string>
								<key>VariableName</key>
								<string>Latest</string>
							</dict>
							<key>{261, 1}</key>
							<dict>
								<key>OutputName</key>
								<string>Published</string>
								<key>OutputUUID</key>
								<string>626EE94D-D2FF-41F3-AED9-AEBFBFDE886F</string>
								<key>Type</key>
								<string>ActionOutput</string>
							</dict>
							<key>{384, 1}</key>
							<dict>
								<key>OutputName</key>
								<string>Release Notes</string>
								<key>OutputUUID</key>
								<string>B5B05A26-CA2D-43B0-913F-7625FEAF1820</string>
								<key>Type</key>
								<string>ActionOutput</string>
							</dict>
							<key>{481, 1}</key>
							<dict>
								<key>Aggrandizements</key>
								<array>
									<dict>
										<key>CoercionItemClass</key>
										<string>WFURLContentItem</string>
										<key>Type</key>
										<string>WFCoercionVariableAggrandizement</string>
									</dict>
								</array>
								<key>OutputName</key>
								<string>Download</string>
								<key>OutputUUID</key>
								<string>BEDD3813-62F8-408A-A8F1-9994B836055B</string>
								<key>Type</key>
								<string>ActionOutput</string>
							</dict>
						</dict>
						<key>string</key>
						<string>&lt;!--Update Available--&gt; 
&lt;!----&gt;
      &lt;div&gt;&lt;center&gt;
        &lt;h1&gt;New Version Available&lt;/h1&gt;&lt;/center&gt;
        &lt;p&gt;&lt;center&gt;&lt;h3&gt;Version ￼ →￼&lt;/h3&gt;&lt;/center&gt;&lt;/p&gt;
        
&lt;!--Latest Version &amp; Release Date--&gt;
        &lt;p style="padding-left: 10px;"&gt;￼ v￼ was released on ￼.&lt;/p&gt;

&lt;!--Notes--&gt;
        &lt;p&gt;&lt;h3 style="padding-left: 10px;"&gt;Release Notes&lt;/h3&gt;
        &lt;p style="padding-left: 10px;"&gt;—￼ &lt;/p&gt;&lt;br /&gt;&lt;/p&gt;

&lt;!--Updare Available--&gt;
        &lt;center&gt;&lt;p&gt;
          &lt;a onclick="window.open('￼'); window.close(); "&gt;&lt;button class="update"&gt;UPDATE NOW&lt;/button&gt;&lt;/a&gt;
        &lt;/p&gt;&lt;/center&gt;&lt;br /&gt;
      &lt;/div&gt;
&lt;!----&gt;</string>
					</dict>
					<key>WFSerializationType</key>
					<string>WFTextTokenString</string>
				</dict>
			</dict>
		</dict>
		<dict>
			<key>WFWorkflowActionIdentifier</key>
			<string>is.workflow.actions.conditional</string>
			<key>WFWorkflowActionParameters</key>
			<dict>
				<key>GroupingIdentifier</key>
				<string>E71087D4-423E-4A13-A5AB-BCDEB8F169B5</string>
				<key>UUID</key>
				<string>F890FB1B-0B27-4D6C-ABD6-1E3A41DD8842</string>
				<key>WFControlFlowMode</key>
				<integer>2</integer>
			</dict>
		</dict>
		<dict>
			<key>WFWorkflowActionIdentifier</key>
			<string>is.workflow.actions.gettext</string>
			<key>WFWorkflowActionParameters</key>
			<dict>
				<key>CustomOutputName</key>
				<string>Foot</string>
				<key>UUID</key>
				<string>D76EDBE1-211B-4B15-9AB9-8413FE73BEE1</string>
				<key>WFTextActionText</key>
				<string>    &lt;a onclick="window.open('https://www.bustl.io/'); window.close();;"&gt;
      &lt;div class="foot"&gt;
        &lt;div class="card" style="background-color: #000000;"&gt;
          &lt;div class="grid"&gt;
            &lt;img src="https://i.imgur.com/wU8q8qx.png" style="width: 50px; height: 50px; margin-top: 0px; margin-bottom: 0px;" /&gt;
            &lt;div class="grid"&gt;
               &lt;center&gt; 
               &lt;!-- &lt;img src="https://i.imgur.com/BLtjvIN.png" style="width:200px; align-items: center; margin-left: 1em; margin-right: 1em; margin-top: 0; margin-bottom: 0;" /&gt;--&gt;
              &lt;/center&gt; 
               &lt;span style="color: white; font-size: 20px; align-items: right; text-align: right; margin-right: auto; margin-top: 0; margin-bottom: 0;"&gt;Bustl.•io Updater&lt;/span&gt;
            &lt;/div&gt;
          &lt;/div&gt;
        &lt;/div&gt;
      &lt;/div&gt;
    &lt;/a&gt;
&lt;!----&gt;
  &lt;/body&gt;
&lt;/html&gt;</string>
			</dict>
		</dict>
		<dict>
			<key>WFWorkflowActionIdentifier</key>
			<string>is.workflow.actions.gettext</string>
			<key>WFWorkflowActionParameters</key>
			<dict>
				<key>UUID</key>
				<string>F9CB3E22-2075-4A74-96A5-9966C66B550C</string>
				<key>WFTextActionText</key>
				<dict>
					<key>Value</key>
					<dict>
						<key>attachmentsByRange</key>
						<dict>
							<key>{0, 1}</key>
							<dict>
								<key>OutputName</key>
								<string>Head</string>
								<key>OutputUUID</key>
								<string>ECF13BBC-2EB7-442F-BABC-7902A9144658</string>
								<key>Type</key>
								<string>ActionOutput</string>
							</dict>
							<key>{10, 1}</key>
							<dict>
								<key>OutputName</key>
								<string>If Result</string>
								<key>OutputUUID</key>
								<string>F890FB1B-0B27-4D6C-ABD6-1E3A41DD8842</string>
								<key>Type</key>
								<string>ActionOutput</string>
							</dict>
							<key>{20, 1}</key>
							<dict>
								<key>OutputName</key>
								<string>Foot</string>
								<key>OutputUUID</key>
								<string>D76EDBE1-211B-4B15-9AB9-8413FE73BEE1</string>
								<key>Type</key>
								<string>ActionOutput</string>
							</dict>
						</dict>
						<key>string</key>
						<string>￼
&lt;!----&gt;
￼
&lt;!----&gt;
￼</string>
					</dict>
					<key>WFSerializationType</key>
					<string>WFTextTokenString</string>
				</dict>
			</dict>
		</dict>
		<dict>
			<key>WFWorkflowActionIdentifier</key>
			<string>is.workflow.actions.base64encode</string>
			<key>WFWorkflowActionParameters</key>
			<dict>
				<key>UUID</key>
				<string>3B0CE705-9465-4C85-AC21-1E1C39159722</string>
				<key>WFBase64LineBreakMode</key>
				<string>None</string>
				<key>WFInput</key>
				<dict>
					<key>Value</key>
					<dict>
						<key>OutputName</key>
						<string>Text</string>
						<key>OutputUUID</key>
						<string>F9CB3E22-2075-4A74-96A5-9966C66B550C</string>
						<key>Type</key>
						<string>ActionOutput</string>
					</dict>
					<key>WFSerializationType</key>
					<string>WFTextTokenAttachment</string>
				</dict>
			</dict>
		</dict>
		<dict>
			<key>WFWorkflowActionIdentifier</key>
			<string>is.workflow.actions.url</string>
			<key>WFWorkflowActionParameters</key>
			<dict>
				<key>Show-WFURLActionURL</key>
				<true/>
				<key>UUID</key>
				<string>C0C576A8-6D0D-4D3C-A8D6-191CBC2575F9</string>
				<key>WFURLActionURL</key>
				<dict>
					<key>Value</key>
					<dict>
						<key>attachmentsByRange</key>
						<dict>
							<key>{36, 1}</key>
							<dict>
								<key>OutputName</key>
								<string>Base64 Encoded</string>
								<key>OutputUUID</key>
								<string>3B0CE705-9465-4C85-AC21-1E1C39159722</string>
								<key>Type</key>
								<string>ActionOutput</string>
							</dict>
						</dict>
						<key>string</key>
						<string>data:text/html;charset=utf-8;base64,￼</string>
					</dict>
					<key>WFSerializationType</key>
					<string>WFTextTokenString</string>
				</dict>
			</dict>
		</dict>
		<dict>
			<key>WFWorkflowActionIdentifier</key>
			<string>is.workflow.actions.openurl</string>
			<key>WFWorkflowActionParameters</key>
			<dict>
				<key>Show-WFInput</key>
				<true/>
				<key>UUID</key>
				<string>2113BE96-704D-4A79-85B2-A6AFFD825CFF</string>
				<key>WFInput</key>
				<dict>
					<key>Value</key>
					<dict>
						<key>OutputName</key>
						<string>URL</string>
						<key>OutputUUID</key>
						<string>C0C576A8-6D0D-4D3C-A8D6-191CBC2575F9</string>
						<key>Type</key>
						<string>ActionOutput</string>
					</dict>
					<key>WFSerializationType</key>
					<string>WFTextTokenAttachment</string>
				</dict>
			</dict>
		</dict>
		<dict>
			<key>WFWorkflowActionIdentifier</key>
			<string>is.workflow.actions.delay</string>
			<key>WFWorkflowActionParameters</key>
			<dict/>
		</dict>
		<dict>
			<key>WFWorkflowActionIdentifier</key>
			<string>is.workflow.actions.comment</string>
			<key>WFWorkflowActionParameters</key>
			<dict>
				<key>WFCommentActionText</key>
				<string>

</string>
			</dict>
		</dict>
		<dict>
			<key>WFWorkflowActionIdentifier</key>
			<string>is.workflow.actions.output</string>
			<key>WFWorkflowActionParameters</key>
			<dict>
				<key>WFNoOutputSurfaceBehavior</key>
				<string>Do Nothing</string>
				<key>WFOutput</key>
				<dict>
					<key>Value</key>
					<dict>
						<key>attachmentsByRange</key>
						<dict>
							<key>{0, 1}</key>
							<dict>
								<key>Aggrandizements</key>
								<array>
									<dict>
										<key>CoercionItemClass</key>
										<string>WFBooleanContentItem</string>
										<key>Type</key>
										<string>WFCoercionVariableAggrandizement</string>
									</dict>
								</array>
								<key>Type</key>
								<string>Variable</string>
								<key>VariableName</key>
								<string>Up To Date</string>
							</dict>
						</dict>
						<key>string</key>
						<string>￼</string>
					</dict>
					<key>WFSerializationType</key>
					<string>WFTextTokenString</string>
				</dict>
				<key>WFResponse</key>
				<dict>
					<key>Value</key>
					<dict>
						<key>attachmentsByRange</key>
						<dict>
							<key>{0, 1}</key>
							<dict>
								<key>Aggrandizements</key>
								<array>
									<dict>
										<key>CoercionItemClass</key>
										<string>WFBooleanContentItem</string>
										<key>Type</key>
										<string>WFCoercionVariableAggrandizement</string>
									</dict>
								</array>
								<key>Type</key>
								<string>Variable</string>
								<key>VariableName</key>
								<string>Up To Date</string>
							</dict>
						</dict>
						<key>string</key>
						<string>￼</string>
					</dict>
					<key>WFSerializationType</key>
					<string>WFTextTokenString</string>
				</dict>
			</dict>
		</dict>
		<dict>
			<key>WFWorkflowActionIdentifier</key>
			<string>is.workflow.actions.comment</string>
			<key>WFWorkflowActionParameters</key>
			<dict>
				<key>WFCommentActionText</key>
				<string>INTEGRITY Updater
                                        By  @̳̬̙͊ͪ͑̂ș̓͗c̰̗̺̹̎̃͑ͨ̉o̝̙̾̿́t̠ͮͧ͆t̨̠͈͒͂͌̽̈́̚͜͟d͛͆ͣw͖͙ͬŗ͎̩ͤ̒̒̓̿̚

𝐈𝐍𝐓𝐄𝐆𝐑𝐈𝐓𝐘 Framework
Copyright © 2021 Scott Wright

Permission is hereby granted, free of charge, to any person obtaining a copy of this software and associated documentation files (the "Software"), to deal in the Software without restriction, including without limitation the rights to use, copy, modify, merge, publish, distribute, sublicense, and/or sell copies of the Software, and to permit persons to whom the Software is furnished to do so, subject to the following conditions:

The above copyright notice and this permission notice shall be included in all copies or substantial portions of the Software.

THE SOFTWARE IS PROVIDED "AS IS", WITHOUT WARRANTY OF ANY KIND, EXPRESS OR IMPLIED, INCLUDING BUT NOT LIMITED TO THE WARRANTIES OF MERCHANTABILITY, FITNESS FOR A PARTICULAR PURPOSE AND NONINFRINGEMENT. IN NO EVENT SHALL THE AUTHORS OR COPYRIGHT HOLDERS BE LIABLE FOR ANY CLAIM, DAMAGES OR OTHER LIABILITY, WHETHER IN AN ACTION OF CONTRACT, TORT OR OTHERWISE, ARISING FROM, OUT OF OR IN CONNECTION WITH THE SOFTWARE OR THE USE OR OTHER DEALINGS IN THE SOFTWARE.
</string>
			</dict>
		</dict>
	</array>
	<key>WFWorkflowClientVersion</key>
	<string>1134</string>
	<key>WFWorkflowHasOutputFallback</key>
	<false/>
	<key>WFWorkflowHasShortcutInputVariables</key>
	<true/>
	<key>WFWorkflowIcon</key>
	<dict>
		<key>WFWorkflowIconGlyphNumber</key>
		<integer>59516</integer>
		<key>WFWorkflowIconStartColor</key>
		<integer>4274264319</integer>
	</dict>
	<key>WFWorkflowImportQuestions</key>
	<array/>
	<key>WFWorkflowInputContentItemClasses</key>
	<array>
		<string>WFStringContentItem</string>
		<string>WFGenericFileContentItem</string>
	</array>
	<key>WFWorkflowMinimumClientVersion</key>
	<integer>1113</integer>
	<key>WFWorkflowMinimumClientVersionString</key>
	<string>1113</string>
	<key>WFWorkflowNoInputBehavior</key>
	<dict>
		<key>Name</key>
		<string>WFWorkflowNoInputBehaviorGetClipboard</string>
		<key>Parameters</key>
		<dict/>
	</dict>
	<key>WFWorkflowOutputContentItemClasses</key>
	<array>
		<string>WFBooleanContentItem</string>
		<string>WFDictionaryContentItem</string>
	</array>
	<key>WFWorkflowTypes</key>
	<array/>
</dict>
</plist>
